README.rst
setup.py
geoip_lastlog/__init__.py
geoip_lastlog.egg-info/PKG-INFO
geoip_lastlog.egg-info/SOURCES.txt
geoip_lastlog.egg-info/dependency_links.txt
geoip_lastlog.egg-info/entry_points.txt
geoip_lastlog.egg-info/not-zip-safe
geoip_lastlog.egg-info/requires.txt
geoip_lastlog.egg-info/top_level.txt