Metadata-Version: 1.1
Name: geoip-lastlog
Version: 0.6
Summary: GeoIP-based location for the last logins
Home-page: https://github.com/FedericoCeratto/geoip-lastlog
Author: Federico Ceratto
Author-email: federico.ceratto@gmail.com
License: AGPLv3+
Keywords: ssh security
Platform: Linux
Classifier: Environment :: Console
Classifier: License :: OSI Approved :: GNU Affero General Public License v3 or later (AGPLv3+)
Classifier: Natural Language :: English
Classifier: Operating System :: POSIX :: Linux
Classifier: Programming Language :: Python
Classifier: Programming Language :: Python :: 2.7
Classifier: Topic :: Security
